python_cryptography/__init__.py
python_cryptography/example.py
python_cryptography-0.0.3.dist-info/METADATA
python_cryptography-0.0.3.dist-info/WHEEL
python_cryptography-0.0.3.dist-info/licenses/LICENSE
python_cryptography-0.0.3.dist-info/RECORD
