Metadata-Version: 2.4
Name: python_cryptography
Version: 0.0.3
Summary: A package for cryptography
Project-URL: Homepage, https://github.com/kuca4hk/python_cryptography_package
Project-URL: Issues, https://github.com/kuca4hk/python_cryptography_package/issues
Author-email: "Tomas Kunc, Jakub Kucera" <jakub.kucera.01@gmail.com>
License-Expression: MIT
License-File: LICENSE
Classifier: Operating System :: OS Independent
Classifier: Programming Language :: Python :: 3
Requires-Python: >=3.12
